odoo/addons/website_cookiefirst/README.rst
odoo/addons/website_cookiefirst/__init__.py
odoo/addons/website_cookiefirst/__manifest__.py
odoo/addons/website_cookiefirst/data/cookies_policy.xml
odoo/addons/website_cookiefirst/i18n/de.po
odoo/addons/website_cookiefirst/i18n/es.po
odoo/addons/website_cookiefirst/i18n/it.po
odoo/addons/website_cookiefirst/i18n/pt_BR.po
odoo/addons/website_cookiefirst/i18n/website_cookiefirst.pot
odoo/addons/website_cookiefirst/models/__init__.py
odoo/addons/website_cookiefirst/models/res_config_settings.py
odoo/addons/website_cookiefirst/models/website.py
odoo/addons/website_cookiefirst/readme/CONFIGURE.md
odoo/addons/website_cookiefirst/readme/CONTRIBUTORS.md
odoo/addons/website_cookiefirst/readme/DESCRIPTION.md
odoo/addons/website_cookiefirst/static/description/icon.png
odoo/addons/website_cookiefirst/static/description/index.html
odoo/addons/website_cookiefirst/tests/__init__.py
odoo/addons/website_cookiefirst/tests/test_res_config_settings.py
odoo/addons/website_cookiefirst/tests/test_website.py
odoo/addons/website_cookiefirst/views/res_config_settings_views.xml
odoo/addons/website_cookiefirst/views/website_template.xml
odoo_addon_website_cookiefirst-19.0.1.0.0.2.dist-info/METADATA
odoo_addon_website_cookiefirst-19.0.1.0.0.2.dist-info/WHEEL
odoo_addon_website_cookiefirst-19.0.1.0.0.2.dist-info/top_level.txt
odoo_addon_website_cookiefirst-19.0.1.0.0.2.dist-info/RECORD
